{
  "hash": "e9356182",
  "configHash": "604e759f",
  "lockfileHash": "c564f01c",
  "browserHash": "7781294a",
  "optimized": {
    "vue": {
      "src": "../../../node_modules/vue/dist/vue.runtime.esm-bundler.js",
      "file": "vue.js",
      "fileHash": "02138f42",
      "needsInterop": false
    },
    "vitepress > @vue/devtools-api": {
      "src": "../../../node_modules/@vue/devtools-api/dist/index.js",
      "file": "vitepress___@vue_devtools-api.js",
      "fileHash": "9286c452",
      "needsInterop": false
    },
    "vitepress > @vueuse/core": {
      "src": "../../../node_modules/@vueuse/core/index.mjs",
      "file": "vitepress___@vueuse_core.js",
      "fileHash": "b902885f",
      "needsInterop": false
    },
    "@theme/index": {
      "src": "../../../node_modules/vitepress/dist/client/theme-default/index.js",
      "file": "@theme_index.js",
      "fileHash": "bca96806",
      "needsInterop": false
    }
  },
  "chunks": {
    "chunk-6F5JWMBQ": {
      "file": "chunk-6F5JWMBQ.js"
    },
    "chunk-VJWGEPT5": {
      "file": "chunk-VJWGEPT5.js"
    }
  }
}